tarsus_mcp/__init__.py
tarsus_mcp/tools.py
tarsus_mcp-0.1.1.dist-info/METADATA
tarsus_mcp-0.1.1.dist-info/WHEEL
tarsus_mcp-0.1.1.dist-info/RECORD
