Metadata-Version: 2.4
Name: tarsus-mcp
Version: 0.1.1
Summary: MCP Tool Definitions for Tarsus API (Python)
Author-email: Tarsus <support@tarsus.tech>
License: MIT
Requires-Python: >=3.10
Requires-Dist: tarsus-sdk
